{
    "name": "agen:well",
    "version": 18,
    "revisions": [
        {
            "revision": 27,
            "global_revision": 1531833976,
            "author": 9331062,
            "stamp": 1756446371,
            "flags": "R",
            "commentary": "您已成功地重新命名本页: \"well\" 至 \"agen:well\"."
        },
        {
            "revision": 26,
            "global_revision": 1531321712,
            "author": 9331062,
            "stamp": 1754044629,
            "flags": "T",
            "commentary": ""
        },
        {
            "revision": 25,
            "global_revision": 1531317336,
            "author": 7344601,
            "stamp": 1754024015,
            "flags": "A",
            "commentary": "已新增标签：搬运, 规则。"
        },
        {
            "revision": 24,
            "global_revision": 1531309398,
            "author": 9331062,
            "stamp": 1753976586,
            "flags": "S",
            "commentary": ""
        },
        {
            "revision": 23,
            "global_revision": 1531308301,
            "author": 7344601,
            "stamp": 1753971594,
            "flags": "S",
            "commentary": ""
        },
        {
            "revision": 22,
            "global_revision": 1531308277,
            "author": 7344601,
            "stamp": 1753971433,
            "flags": "S",
            "commentary": ""
        },
        {
            "revision": 21,
            "global_revision": 1531308263,
            "author": 7344601,
            "stamp": 1753971354,
            "flags": "S",
            "commentary": ""
        },
        {
            "revision": 20,
            "global_revision": 1531308260,
            "author": 7344601,
            "stamp": 1753971318,
            "flags": "S",
            "commentary": ""
        },
        {
            "revision": 19,
            "global_revision": 1531308245,
            "author": 7344601,
            "stamp": 1753971216,
            "flags": "S",
            "commentary": ""
        },
        {
            "revision": 18,
            "global_revision": 1531308234,
            "author": 7344601,
            "stamp": 1753971165,
            "flags": "S",
            "commentary": ""
        },
        {
            "revision": 17,
            "global_revision": 1531308203,
            "author": 7344601,
            "stamp": 1753971131,
            "flags": "S",
            "commentary": ""
        },
        {
            "revision": 16,
            "global_revision": 1531308190,
            "author": 7344601,
            "stamp": 1753971067,
            "flags": "S",
            "commentary": ""
        },
        {
            "revision": 15,
            "global_revision": 1531308186,
            "author": 7344601,
            "stamp": 1753971026,
            "flags": "S",
            "commentary": ""
        },
        {
            "revision": 14,
            "global_revision": 1531308179,
            "author": 7344601,
            "stamp": 1753970979,
            "flags": "S",
            "commentary": ""
        },
        {
            "revision": 13,
            "global_revision": 1531308171,
            "author": 7344601,
            "stamp": 1753970932,
            "flags": "S",
            "commentary": ""
        },
        {
            "revision": 12,
            "global_revision": 1531308169,
            "author": 7344601,
            "stamp": 1753970896,
            "flags": "S",
            "commentary": ""
        },
        {
            "revision": 11,
            "global_revision": 1531307900,
            "author": 7344601,
            "stamp": 1753969668,
            "flags": "S",
            "commentary": ""
        },
        {
            "revision": 10,
            "global_revision": 1531307874,
            "author": 7344601,
            "stamp": 1753969551,
            "flags": "S",
            "commentary": ""
        },
        {
            "revision": 9,
            "global_revision": 1531307772,
            "author": 7344601,
            "stamp": 1753969105,
            "flags": "S",
            "commentary": ""
        },
        {
            "revision": 8,
            "global_revision": 1531307752,
            "author": 7344601,
            "stamp": 1753969029,
            "flags": "S",
            "commentary": ""
        },
        {
            "revision": 7,
            "global_revision": 1531307739,
            "author": 7344601,
            "stamp": 1753968955,
            "flags": "S",
            "commentary": ""
        },
        {
            "revision": 6,
            "global_revision": 1531307735,
            "author": 7344601,
            "stamp": 1753968931,
            "flags": "S",
            "commentary": ""
        },
        {
            "revision": 5,
            "global_revision": 1531307729,
            "author": 7344601,
            "stamp": 1753968867,
            "flags": "S",
            "commentary": ""
        },
        {
            "revision": 4,
            "global_revision": 1531307692,
            "author": 7344601,
            "stamp": 1753968616,
            "flags": "S",
            "commentary": ""
        },
        {
            "revision": 3,
            "global_revision": 1531307678,
            "author": 7344601,
            "stamp": 1753968536,
            "flags": "S",
            "commentary": ""
        },
        {
            "revision": 2,
            "global_revision": 1531307676,
            "author": 7344601,
            "stamp": 1753968519,
            "flags": "S",
            "commentary": ""
        },
        {
            "revision": 1,
            "global_revision": 1531307666,
            "author": 7344601,
            "stamp": 1753968481,
            "flags": "S",
            "commentary": ""
        },
        {
            "revision": 0,
            "global_revision": 1531307649,
            "author": 7344601,
            "stamp": 1753968377,
            "flags": "N",
            "commentary": ""
        }
    ],
    "files": [],
    "page_id": 1459987491,
    "rating": 2,
    "forum_thread": 17174225,
    "tags": [
        "搬运",
        "规则"
    ],
    "title": "井（施工中）",
    "sitemap_update": 1756446371000,
    "votings": [
        [
            9808112,
            true
        ],
        [
            9879630,
            true
        ]
    ],
    "is_locked": false
}