{
    "title": "Level IF-30",
    "id": 17131396,
    "description": "",
    "last": 1754887522,
    "lastUser": 9419995,
    "started": 1747403844,
    "startedUser": null,
    "postsNum": 2,
    "sticky": false,
    "isLocked": false,
    "version": 1,
    "posts": [
        {
            "id": 7000639,
            "title": "",
            "poster": 9485306,
            "stamp": 1747403861,
            "revisions": [],
            "children": []
        },
        {
            "id": 7105643,
            "title": "捉虫",
            "poster": 9419995,
            "stamp": 1754887522,
            "revisions": [],
            "children": []
        }
    ]
}