{
    "title": "Level IF-322",
    "id": 17235403,
    "description": "",
    "last": 1757133950,
    "lastUser": 8759709,
    "started": 1756449302,
    "startedUser": null,
    "postsNum": 2,
    "sticky": false,
    "isLocked": false,
    "version": 1,
    "posts": [
        {
            "id": 7179372,
            "title": "",
            "poster": 9485306,
            "stamp": 1756449320,
            "revisions": [],
            "children": [
                {
                    "id": 7186095,
                    "title": "",
                    "poster": 8759709,
                    "stamp": 1757133950,
                    "revisions": [],
                    "children": []
                }
            ]
        }
    ]
}