{
    "title": "退坑",
    "id": 17233056,
    "description": "",
    "last": 1762352997,
    "lastUser": 9189492,
    "started": 1756202481,
    "startedUser": null,
    "postsNum": 3,
    "sticky": false,
    "isLocked": false,
    "version": 1,
    "posts": [
        {
            "id": 7407316,
            "title": "",
            "poster": 9189492,
            "stamp": 1762352997,
            "revisions": [],
            "children": []
        },
        {
            "id": 7176712,
            "title": "",
            "poster": 9551083,
            "stamp": 1756346374,
            "revisions": [],
            "children": []
        },
        {
            "id": 7168659,
            "title": "",
            "poster": 9782629,
            "stamp": 1756202501,
            "lastEdit": 1756202517,
            "lastEditBy": 9782629,
            "revisions": [
                {
                    "title": "",
                    "author": 9782629,
                    "id": 8665735,
                    "stamp": 1756202517
                },
                {
                    "title": "",
                    "author": 9782629,
                    "id": 8665733,
                    "stamp": 1756202501
                }
            ],
            "children": []
        }
    ]
}