{
    "title": "Creature IF-15 - “黄藻门”",
    "id": 17281494,
    "description": "",
    "last": 1759588521,
    "lastUser": 8317495,
    "started": 1759396713,
    "startedUser": null,
    "postsNum": 2,
    "sticky": false,
    "isLocked": false,
    "version": 1,
    "posts": [
        {
            "id": 7257057,
            "title": "uv",
            "poster": 8317495,
            "stamp": 1759588521,
            "revisions": [],
            "children": []
        },
        {
            "id": 7241185,
            "title": "N",
            "poster": 9099707,
            "stamp": 1759401829,
            "lastEdit": 1759645869,
            "lastEditBy": 9099707,
            "revisions": [
                {
                    "title": "N",
                    "author": 9099707,
                    "id": 8770537,
                    "stamp": 1759645869
                },
                {
                    "title": "N",
                    "author": 9099707,
                    "id": 8748599,
                    "stamp": 1759401829
                }
            ],
            "children": []
        }
    ]
}