{
    "9483189": {
        "full_name": "qwmike1145",
        "username": "qwmike1145",
        "real_name": "宇哥",
        "gender": "male",
        "birthday": 1081555200000,
        "from": "China Guangxi",
        "website": "u-backrooms.wikidot.com",
        "wikidot_user_since": 1732890660,
        "account_type": "free",
        "activity": 5,
        "fetched_at": 1774412831148,
        "user_id": 9483189
    },
    "9485306": {
        "full_name": "XiaoZI666",
        "username": "xiaozi666",
        "real_name": "孝子、外星人、外星入",
        "wikidot_user_since": 1733044620,
        "account_type": "free",
        "activity": 3,
        "fetched_at": 1774412842041,
        "user_id": 9485306
    }
}