{
    "name": "_404",
    "version": 18,
    "revisions": [
        {
            "revision": 11,
            "global_revision": 1360108754,
            "author": 5713128,
            "stamp": 1614350080,
            "flags": "S",
            "commentary": ""
        },
        {
            "revision": 10,
            "global_revision": 1034147808,
            "author": 5713128,
            "stamp": 1579876739,
            "flags": "S",
            "commentary": ""
        },
        {
            "revision": 9,
            "global_revision": 1034137341,
            "author": 5713128,
            "stamp": 1579835330,
            "flags": "S",
            "commentary": ""
        },
        {
            "revision": 8,
            "global_revision": 1034137281,
            "author": 5713128,
            "stamp": 1579835148,
            "flags": "S",
            "commentary": ""
        },
        {
            "revision": 7,
            "global_revision": 1033868114,
            "author": 4764494,
            "stamp": 1578884930,
            "flags": "S",
            "commentary": ""
        },
        {
            "revision": 6,
            "global_revision": 1033699501,
            "author": 5713128,
            "stamp": 1578221942,
            "flags": "S",
            "commentary": ""
        },
        {
            "revision": 5,
            "global_revision": 1033699485,
            "author": 5713128,
            "stamp": 1578221764,
            "flags": "S",
            "commentary": ""
        },
        {
            "revision": 4,
            "global_revision": 1033699477,
            "author": 5713128,
            "stamp": 1578221719,
            "flags": "S",
            "commentary": ""
        },
        {
            "revision": 3,
            "global_revision": 1033698979,
            "author": 5713128,
            "stamp": 1578219194,
            "flags": "S",
            "commentary": ""
        },
        {
            "revision": 2,
            "global_revision": 1033698976,
            "author": 5713128,
            "stamp": 1578219161,
            "flags": "S",
            "commentary": ""
        },
        {
            "revision": 1,
            "global_revision": 1033698974,
            "author": 5713128,
            "stamp": 1578219124,
            "flags": "S",
            "commentary": ""
        },
        {
            "revision": 0,
            "global_revision": 1033683656,
            "author": 4764494,
            "stamp": 1578150545,
            "flags": "N",
            "commentary": ""
        }
    ],
    "files": [],
    "page_id": 986050770,
    "title": "_404",
    "sitemap_update": 1614350080000,
    "votings": [],
    "is_locked": false
}